pytyped/metrics/__init__.py
pytyped/metrics/common.py
pytyped/metrics/exporter.py
pytyped/metrics/py.typed
pytyped_metrics-2.0.0.dist-info/LICENSE
pytyped_metrics-2.0.0.dist-info/METADATA
pytyped_metrics-2.0.0.dist-info/WHEEL
pytyped_metrics-2.0.0.dist-info/top_level.txt
pytyped_metrics-2.0.0.dist-info/RECORD
